README.md
setup.py
msmhc/__init__.py
msmhc/alt_orf.py
msmhc/common.py
msmhc/decoys.py
msmhc/fdr.py
msmhc/fdr_cli.py
msmhc/generate_cli.py
msmhc/genetic_code.py
msmhc/kozak.py
msmhc/main.py
msmhc/mass.py
msmhc/mutant_sequence.py
msmhc/numerical_peptide_representation.py
msmhc/peptides.py
msmhc/reference_sequence.py
msmhc/sequence.py
msmhc.egg-info/PKG-INFO
msmhc.egg-info/SOURCES.txt
msmhc.egg-info/dependency_links.txt
msmhc.egg-info/entry_points.txt
msmhc.egg-info/requires.txt
msmhc.egg-info/top_level.txt